MANIFEST.in
requirements.txt
setup.cfg
setup.py
bin/get_value_stream_status.py
bin/parse_gocd_cctray.py
gocd_parser/__init__.py
gocd_parser/gocd_argparse.py
gocd_parser/gocd_logger.py
gocd_parser/stream_status.py
gocd_parser/version.py
gocd_parser.egg-info/PKG-INFO
gocd_parser.egg-info/SOURCES.txt
gocd_parser.egg-info/dependency_links.txt
gocd_parser.egg-info/pbr.json
gocd_parser.egg-info/requires.txt
gocd_parser.egg-info/top_level.txt
gocd_parser/handler/__init__.py
gocd_parser/handler/cctray.py
gocd_parser/handler/dashboard.py
gocd_parser/handler/pipeline_groups.py
gocd_parser/handler/status.py
gocd_parser/handler/value_stream.py
gocd_parser/handler/compare/__init__.py
gocd_parser/handler/compare/change.py
gocd_parser/handler/compare/material.py
gocd_parser/handler/history/__init__.py
gocd_parser/handler/history/history_page.py
gocd_parser/pipeline/__init__.py
gocd_parser/pipeline/common.py
gocd_parser/pipeline/job.py
gocd_parser/pipeline/stage.py
gocd_parser/retriever/__init__.py
gocd_parser/retriever/server.py
gocd_parser/retriever/url.py
gocd_parser/value_stream/__init__.py
gocd_parser/value_stream/graph.py
gocd_parser/value_stream/tree.py
gocd_parser/value_stream/recurse/__init__.py
gocd_parser/value_stream/recurse/node.py