Metadata-Version: 1.0
Name: gocd-parser
Version: 1.2.1
Summary: Libraries for parsing GoCD APIs
Home-page: https://github.com/greenmoss/gocd-parser
Author: Kurt Yoder
Author-email: kyoder@gmail.com
License: UNKNOWN
Platform: UNKNOWN
